runs/__init__.py
runs/py.typed
runs-1.2.1.dist-info/LICENSE
runs-1.2.1.dist-info/METADATA
runs-1.2.1.dist-info/WHEEL
runs-1.2.1.dist-info/RECORD
